[{"_业绩归属人":"许二妹","_购买总数量":2006.0,"_拣货单张数":536.0,"_总时长":"01:18:00","_分钟":78.0,"_拣货单效率":6.8718,"_购买数量效率":25.7179,"_小时":1.3,"_拣货单每小时":412.3077,"_个数每小时":1543.0769,"_定值倍数":1.812,"_工资":2436.0},{"_业绩归属人":"王丽娟","_购买总数量":2268.0,"_拣货单张数":550.0,"_总时长":"01:18:00","_分钟":78.0,"_拣货单效率":7.0513,"_购买数量效率":29.0769,"_小时":1.3,"_拣货单每小时":423.0769,"_个数每小时":1744.6154,"_定值倍数":1.8933,"_工资":2679.9},{"_业绩归属人":"沈春霞","_购买总数量":1588.0,"_拣货单张数":542.0,"_总时长":"01:22:00","_分钟":82.0,"_拣货单效率":6.6098,"_购买数量效率":19.3659,"_小时":1.3667,"_拣货单每小时":396.5757,"_个数每小时":1161.9229,"_定值倍数":1.6749,"_工资":2024.7},{"_业绩归属人":"叶路娟","_购买总数量":1708.0,"_拣货单张数":563.0,"_总时长":"01:15:00","_分钟":75.0,"_拣货单效率":7.5067,"_购买数量效率":22.7733,"_小时":1.25,"_拣货单每小时":450.4,"_个数每小时":1366.4,"_定值倍数":1.9121,"_工资":2736.3},{"_业绩归属人":"陶亚玲","_购买总数量":1276.0,"_拣货单张数":518.0,"_总时长":"01:21:00","_分钟":81.0,"_拣货单效率":6.3951,"_购买数量效率":15.7531,"_小时":1.35,"_拣货单每小时":383.7037,"_个数每小时":945.1852,"_定值倍数":1.5828,"_工资":1748.4},{"_业绩归属人":"程雪","_购买总数量":1420.0,"_拣货单张数":455.0,"_总时长":"01:15:00","_分钟":75.0,"_拣货单效率":6.0667,"_购买数量效率":18.9333,"_小时":1.25,"_拣货单每小时":364.0,"_个数每小时":1136.0,"_定值倍数":1.552,"_工资":1656.0},{"_业绩归属人":"段二静","_购买总数量":1484.0,"_拣货单张数":523.0,"_总时长":"01:24:00","_分钟":84.0,"_拣货单效率":6.2262,"_购买数量效率":17.6667,"_小时":1.4,"_拣货单每小时":373.5714,"_个数每小时":1060.0,"_定值倍数":1.5705,"_工资":1711.5},{"_业绩归属人":"豆亚琪","_购买总数量":2103.0,"_拣货单张数":557.0,"_总时长":"01:20:00","_分钟":80.0,"_拣货单效率":6.9625,"_购买数量效率":26.2875,"_小时":1.3333,"_拣货单每小时":417.7604,"_个数每小时":1577.2894,"_定值倍数":1.8388,"_工资":2516.4},{"_业绩归属人":"潘琦","_购买总数量":1580.0,"_拣货单张数":458.0,"_总时长":"01:15:00","_分钟":75.0,"_拣货单效率":6.1067,"_购买数量效率":21.0667,"_小时":1.25,"_拣货单每小时":366.4,"_个数每小时":1264.0,"_定值倍数":1.5876,"_工资":1762.8},{"_业绩归属人":"杨艳","_购买总数量":890.0,"_拣货单张数":339.0,"_总时长":"01:05:00","_分钟":65.0,"_拣货单效率":5.2154,"_购买数量效率":13.6923,"_小时":1.0833,"_拣货单每小时":312.9327,"_个数每小时":821.5637,"_定值倍数":1.3015,"_工资":904.5},{"_业绩归属人":"张鲜","_购买总数量":1176.0,"_拣货单张数":278.0,"_总时长":"00:53:00","_分钟":53.0,"_拣货单效率":5.2453,"_购买数量效率":22.1887,"_小时":0.8833,"_拣货单每小时":314.7289,"_个数每小时":1331.371,"_定值倍数":1.4155,"_工资":1246.5},{"_业绩归属人":"陈雪艳","_购买总数量":1651.0,"_拣货单张数":481.0,"_总时长":"01:30:00","_分钟":90.0,"_拣货单效率":5.3444,"_购买数量效率":18.3444,"_小时":1.5,"_拣货单每小时":320.6667,"_个数每小时":1100.6667,"_定值倍数":1.3883,"_工资":1164.9},{"_业绩归属人":"郑会亚","_购买总数量":6741.0,"_拣货单张数":466.0,"_总时长":"01:30:00","_分钟":90.0,"_拣货单效率":5.1778,"_购买数量效率":74.9,"_小时":1.5,"_拣货单每小时":310.6667,"_个数每小时":4494.0,"_定值倍数":2.0675,"_工资":3202.5},{"_业绩归属人":"张亚娟","_购买总数量":1168.0,"_拣货单张数":298.0,"_总时长":"01:30:00","_分钟":90.0,"_拣货单效率":3.3111,"_购买数量效率":12.9778,"_小时":1.5,"_拣货单每小时":198.6667,"_个数每小时":778.6667,"_定值倍数":0.8805,"_工资":0.0},{"_业绩归属人":"罗进芳","_购买总数量":1814.0,"_拣货单张数":468.0,"_总时长":"01:28:00","_分钟":88.0,"_拣货单效率":5.3182,"_购买数量效率":20.6136,"_小时":1.4667,"_拣货单每小时":319.0837,"_个数每小时":1236.7901,"_定值倍数":1.4112,"_工资":1233.6},{"_业绩归属人":"吴晓洁","_购买总数量":3529.0,"_拣货单张数":430.0,"_总时长":"01:20:00","_分钟":80.0,"_拣货单效率":5.375,"_购买数量效率":44.1125,"_小时":1.3333,"_拣货单每小时":322.5081,"_个数每小时":2646.8162,"_定值倍数":1.7208,"_工资":2162.4},{"_业绩归属人":"蔡学婷","_购买总数量":1028.0,"_拣货单张数":366.0,"_总时长":"01:15:00","_分钟":75.0,"_拣货单效率":4.88,"_购买数量效率":13.7067,"_小时":1.25,"_拣货单每小时":292.8,"_个数每小时":822.4,"_定值倍数":1.2291,"_工资":687.3},{"_业绩归属人":"张琼琼","_购买总数量":545.0,"_拣货单张数":227.0,"_总时长":"01:00:00","_分钟":60.0,"_拣货单效率":3.7833,"_购买数量效率":9.0833,"_小时":1.0,"_拣货单每小时":227.0,"_个数每小时":545.0,"_定值倍数":0.9334,"_工资":0.0},{"_业绩归属人":"李娟红","_购买总数量":878.0,"_拣货单张数":250.0,"_总时长":"01:10:00","_分钟":70.0,"_拣货单效率":3.5714,"_购买数量效率":12.5429,"_小时":1.1667,"_拣货单每小时":214.2796,"_个数每小时":752.5499,"_定值倍数":0.9313,"_工资":0.0},{"_业绩归属人":"董淑红","_购买总数量":2675.0,"_拣货单张数":226.0,"_总时长":"01:15:00","_分钟":75.0,"_拣货单效率":3.0133,"_购买数量效率":35.6667,"_小时":1.25,"_拣货单每小时":180.8,"_个数每小时":2140.0,"_定值倍数":1.103,"_工资":309.0},{"_业绩归属人":"郭群英","_购买总数量":2338.0,"_拣货单张数":380.0,"_总时长":"01:30:00","_分钟":90.0,"_拣货单效率":4.2222,"_购买数量效率":25.9778,"_小时":1.5,"_拣货单每小时":253.3333,"_个数每小时":1558.6667,"_定值倍数":1.242,"_工资":726.0},{"_业绩归属人":"刘宏巧","_购买总数量":1078.0,"_拣货单张数":292.0,"_总时长":"01:15:00","_分钟":75.0,"_拣货单效率":3.8933,"_购买数量效率":14.3733,"_小时":1.25,"_拣货单每小时":233.6,"_个数每小时":862.4,"_定值倍数":1.0241,"_工资":72.3},{"_业绩归属人":"蒋娜娜","_购买总数量":2840.0,"_拣货单张数":380.0,"_总时长":"01:17:00","_分钟":77.0,"_拣货单效率":4.9351,"_购买数量效率":36.8831,"_小时":1.2833,"_拣货单每小时":296.1116,"_个数每小时":2213.0445,"_定值倍数":1.5342,"_工资":1602.6},{"_业绩归属人":"任婉英","_购买总数量":1449.0,"_拣货单张数":257.0,"_总时长":"01:50:00","_分钟":110.0,"_拣货单效率":2.3364,"_购买数量效率":13.1727,"_小时":1.8333,"_拣货单每小时":140.1844,"_个数每小时":790.378,"_定值倍数":0.6721,"_工资":0.0},{"_业绩归属人":"欧于书","_购买总数量":821.0,"_拣货单张数":217.0,"_总时长":"01:09:00","_分钟":69.0,"_拣货单效率":3.1449,"_购买数量效率":11.8986,"_小时":1.15,"_拣货单每小时":188.6957,"_个数每小时":713.913,"_定值倍数":0.8309,"_工资":0.0},{"_业绩归属人":"王泽云","_购买总数量":537.0,"_拣货单张数":230.0,"_总时长":"01:00:00","_分钟":60.0,"_拣货单效率":3.8333,"_购买数量效率":8.95,"_小时":1.0,"_拣货单每小时":230.0,"_个数每小时":537.0,"_定值倍数":0.9425,"_工资":0.0},{"_业绩归属人":"栗玉娟","_购买总数量":1643.0,"_拣货单张数":382.0,"_总时长":"01:18:00","_分钟":78.0,"_拣货单效率":4.8974,"_购买数量效率":21.0641,"_小时":1.3,"_拣货单每小时":293.8462,"_个数每小时":1263.8462,"_定值倍数":1.326,"_工资":978.0},{"_业绩归属人":"王芳婷","_购买总数量":1311.0,"_拣货单张数":368.0,"_总时长":"01:17:00","_分钟":77.0,"_拣货单效率":4.7792,"_购买数量效率":17.026,"_小时":1.2833,"_拣货单每小时":286.7607,"_个数每小时":1021.585,"_定值倍数":1.2493,"_工资":747.9},{"_业绩归属人":"张海荣","_购买总数量":1023.0,"_拣货单张数":350.0,"_总时长":"02:00:00","_分钟":120.0,"_拣货单效率":2.9167,"_购买数量效率":8.525,"_小时":2.0,"_拣货单每小时":175.0,"_个数每小时":511.5,"_定值倍数":0.7388,"_工资":0.0},{"_业绩归属人":"桑永梅","_购买总数量":3695.0,"_拣货单张数":406.0,"_总时长":"01:25:00","_分钟":85.0,"_拣货单效率":4.7765,"_购买数量效率":43.4706,"_小时":1.4167,"_拣货单每小时":286.5815,"_个数每小时":2608.1739,"_定值倍数":1.5831,"_工资":1749.3},{"_业绩归属人":"张艳平","_购买总数量":6471.0,"_拣货单张数":360.0,"_总时长":"01:32:00","_分钟":92.0,"_拣货单效率":3.913,"_购买数量效率":70.337,"_小时":1.5333,"_拣货单每小时":234.7877,"_个数每小时":4220.3091,"_定值倍数":1.7362,"_工资":2208.6},{"_业绩归属人":"杨胜菊","_购买总数量":1711.0,"_拣货单张数":333.0,"_总时长":"01:30:00","_分钟":90.0,"_拣货单效率":3.7,"_购买数量效率":19.0111,"_小时":1.5,"_拣货单每小时":222.0,"_个数每小时":1140.6667,"_定值倍数":1.0409,"_工资":122.7},{"_业绩归属人":"刘富平","_购买总数量":1681.0,"_拣货单张数":212.0,"_总时长":"01:37:00","_分钟":97.0,"_拣货单效率":2.1856,"_购买数量效率":17.3299,"_小时":1.6167,"_拣货单每小时":131.1313,"_个数每小时":1039.7724,"_定值倍数":0.692,"_工资":0.0},{"_业绩归属人":"封红艳","_购买总数量":1199.0,"_拣货单张数":344.0,"_总时长":"02:00:00","_分钟":120.0,"_拣货单效率":2.8667,"_购买数量效率":9.9917,"_小时":2.0,"_拣货单每小时":172.0,"_个数每小时":599.5,"_定值倍数":0.7466,"_工资":0.0},{"_业绩归属人":"顾洁","_购买总数量":3048.0,"_拣货单张数":424.0,"_总时长":"01:28:00","_分钟":88.0,"_拣货单效率":4.8182,"_购买数量效率":34.6364,"_小时":1.4667,"_拣货单每小时":289.0843,"_个数每小时":2078.1346,"_定值倍数":1.4804,"_工资":1441.2},{"_业绩归属人":"温利娇","_购买总数量":2535.0,"_拣货单张数":399.0,"_总时长":"01:17:00","_分钟":77.0,"_拣货单效率":5.1818,"_购买数量效率":32.9221,"_小时":1.2833,"_拣货单每小时":310.9172,"_个数每小时":1975.376,"_定值倍数":1.5375,"_工资":1612.5},{"_业绩归属人":"郭红霞","_购买总数量":632.0,"_拣货单张数":111.0,"_总时长":"00:40:00","_分钟":40.0,"_拣货单效率":2.775,"_购买数量效率":15.8,"_小时":0.6667,"_拣货单每小时":166.4917,"_个数每小时":947.9526,"_定值倍数":0.8002,"_工资":0.0},{"_业绩归属人":"杨雪","_购买总数量":2003.0,"_拣货单张数":300.0,"_总时长":"01:29:00","_分钟":89.0,"_拣货单效率":3.3708,"_购买数量效率":22.5056,"_小时":1.4833,"_拣货单每小时":202.2517,"_个数每小时":1350.3674,"_定值倍数":1.0139,"_工资":41.7}]